automate_excel/__init__.py
automate_excel/config.py
automate_excel/main.py
src/__init__.py
src/config.py
src/main.py
automate_excel-0.0.221.dist-info/COPYING
automate_excel-0.0.221.dist-info/METADATA
automate_excel-0.0.221.dist-info/WHEEL
automate_excel-0.0.221.dist-info/top_level.txt
automate_excel-0.0.221.dist-info/RECORD
