Metadata-Version: 2.1
Name: automate-excel
Version: 0.0.221
Summary: A library for automating existing spreadsheets.
Home-page: https://github.com/chrispcharlton/automate_excel
Author: Chris Charlton
Author-email: chrispcharlton@gmail.com
License: UNKNOWN
Platform: UNKNOWN
Classifier: Programming Language :: Python :: 3
Classifier: Operating System :: Microsoft :: Windows
Requires-Python: >=3.7
Requires-Dist: pywin32
Requires-Dist: pandas
Requires-Dist: numpy
